headlines/__init__.py
headlines-0.0.2.dist-info/DESCRIPTION.rst
headlines-0.0.2.dist-info/METADATA
headlines-0.0.2.dist-info/RECORD
headlines-0.0.2.dist-info/WHEEL
headlines-0.0.2.dist-info/entry_points.txt
headlines-0.0.2.dist-info/metadata.json
headlines-0.0.2.dist-info/top_level.txt
