Metadata-Version: 2.0
Name: headlines
Version: 0.0.2
Summary: Headlines for the terminal.
Home-page: https://github.com/feluxe/headlines
Author: Felix Meyer-Wolters
Author-email: felix@meyerwolters.de
Maintainer: Felix Meyer-Wolters
Maintainer-email: felix@meyerwolters.de
License: unlicensed
Download-URL: https://github.com/feluxe/headlines/tarball/0.0.2
Keywords: headlines,terminal
Platform: 
